dvr.py
dvr_tools-1.1.2.dist-info/METADATA
dvr_tools-1.1.2.dist-info/WHEEL
dvr_tools-1.1.2.dist-info/entry_points.txt
dvr_tools-1.1.2.dist-info/top_level.txt
dvr_tools-1.1.2.dist-info/RECORD
