Metadata-Version: 2.4
Name: dvr-tools
Version: 1.1.2
Summary: A command-line interface for managing DVR tools.
Author-email: Ilya Krivoshein <htctomsk634@gmail.com>
License: MIT
Keywords: DVR,tools,command-line,video,recorder
Classifier: Programming Language :: Python :: 3
Classifier: License :: OSI Approved :: MIT License
Classifier: Operating System :: OS Independent
Requires-Dist: click
Requires-Dist: requests
Requires-Dist: pytest
